<?xml version="1.0" encoding="UTF-8"?>
<are:Ares_odpovedi vystup_format="XML" odpoved_typ="es" Id="ares" xsi:schemaLocation="http://wwwinfo.mfcr.cz/ares/xml_doc/schemas/ares/ares_answer_es/v_1.0.0 http://wwwinfo.mfcr.cz/ares/xml_doc/schemas/ares/ares_answer_es/v_1.0.0/ares_answer_es.xsd" xmlns:are="http://wwwinfo.mfcr.cz/ares/xml_doc/schemas/ares/ares_answer_es/v_1.0.0" xmlns:dtt="http://wwwinfo.mfcr.cz/ares/xml_doc/schemas/ares/ares_datatypes/v_1.0.4" xmlns:udt="http://wwwinfo.mfcr.cz/ares/xml_doc/schemas/uvis_datatypes/v_1.0.1" xmlns:xsi="http://www.w3.org/2001/XMLSchema-instance">
<are:Odpoved>
<dtt:V>
<dtt:S>
<dtt:ico>00938475</dtt:ico>
<dtt:pf>105</dtt:pf>
<dtt:ojm>Michal Boháč</dtt:ojm>
<dtt:jmn>Praha 7, Holešovice, V zákoutí 1029/4</dtt:jmn>
<dtt:res>0</dtt:res>
<dtt:ros>1</dtt:ros>
</dtt:S>
<dtt:S>
<dtt:ico>26199327</dtt:ico>
<dtt:pf>112</dtt:pf>
<dtt:ojm>IncStav s.r.o.</dtt:ojm>
<dtt:jmn>Praha 7, Holešovice, V zákoutí 1029/4</dtt:jmn>
<dtt:or>0</dtt:or>
<dtt:res>0</dtt:res>
<dtt:rzp>0</dtt:rzp>
<dtt:dph>1</dtt:dph>
<dtt:p_dph>dic=26199327</dtt:p_dph>
<dtt:ros>0</dtt:ros>
</dtt:S>
<dtt:S>
<dtt:ico>45789835</dtt:ico>
<dtt:pf>112</dtt:pf>
<dtt:ojm>Totem, spol. s r.o.</dtt:ojm>
<dtt:jmn>Praha 7, Holešovice, V zákoutí 1029/4</dtt:jmn>
<dtt:or>0</dtt:or>
<dtt:res>0</dtt:res>
<dtt:rzp>0</dtt:rzp>
<dtt:dph>1</dtt:dph>
<dtt:p_dph>dic=45789835</dtt:p_dph>
<dtt:ros>0</dtt:ros>
</dtt:S>
<dtt:S>
<dtt:ico>45800421</dtt:ico>
<dtt:pf>112</dtt:pf>
<dtt:ojm>InCon s.r.o. &quot;v likvidaci&quot;</dtt:ojm>
<dtt:jmn>Praha 7, Holešovice, V zákoutí 1029/4</dtt:jmn>
<dtt:or>0</dtt:or>
<dtt:res>0</dtt:res>
<dtt:rzp>0</dtt:rzp>
<dtt:dph>1</dtt:dph>
<dtt:p_dph>dic=45800421</dtt:p_dph>
<dtt:ros>0</dtt:ros>
</dtt:S>
<dtt:S>
<dtt:ico>47534893</dtt:ico>
<dtt:pf>112</dtt:pf>
<dtt:ojm>COSTRAD - MEDAL s.r.o.</dtt:ojm>
<dtt:jmn>Praha 7, Holešovice, V zákoutí 1029/4</dtt:jmn>
<dtt:or>0</dtt:or>
<dtt:res>0</dtt:res>
<dtt:rzp>0</dtt:rzp>
<dtt:ros>0</dtt:ros>
</dtt:S>
<dtt:S>
<dtt:ico>48026689</dtt:ico>
<dtt:pf>112</dtt:pf>
<dtt:ojm>Hermes,obchodní a konzultační spol.s r.o.</dtt:ojm>
<dtt:jmn>Praha 7, Holešovice, V zákoutí 1029/4</dtt:jmn>
<dtt:or>0</dtt:or>
<dtt:res>0</dtt:res>
<dtt:rzp>0</dtt:rzp>
<dtt:dph>1</dtt:dph>
<dtt:p_dph>dic=48026689</dtt:p_dph>
<dtt:ros>0</dtt:ros>
</dtt:S>
<dtt:S>
<dtt:ico>63092336</dtt:ico>
<dtt:pf>101</dtt:pf>
<dtt:ojm>Ilona DUSSLOVÁ</dtt:ojm>
<dtt:jmn>Praha 7, Holešovice, V zákoutí 1029/4</dtt:jmn>
<dtt:res>0</dtt:res>
<dtt:rzp>0</dtt:rzp>
<dtt:ros>0</dtt:ros>
</dtt:S>
<dtt:S>
<dtt:ico>71534431</dtt:ico>
<dtt:pf>101</dtt:pf>
<dtt:ojm>Pavel NOVOTNÝ</dtt:ojm>
<dtt:jmn>Praha 7, Holešovice, V zákoutí 1029/4</dtt:jmn>
<dtt:res>0</dtt:res>
<dtt:rzp>0</dtt:rzp>
<dtt:ros>0</dtt:ros>
</dtt:S>
<dtt:S>
<dtt:ico>76500071</dtt:ico>
<dtt:pf>101</dtt:pf>
<dtt:ojm>Tomáš Hospodka</dtt:ojm>
<dtt:jmn>Praha 7, Holešovice, V zákoutí 1029/4</dtt:jmn>
<dtt:res>0</dtt:res>
<dtt:rzp>0</dtt:rzp>
<dtt:ros>0</dtt:ros>
</dtt:S>
<dtt:S>
<dtt:ico>86566725</dtt:ico>
<dtt:pf>101</dtt:pf>
<dtt:ojm>Zita Čelikovská</dtt:ojm>
<dtt:jmn>Praha 7, Holešovice, V zákoutí 1029/4</dtt:jmn>
<dtt:res>0</dtt:res>
<dtt:rzp>0</dtt:rzp>
<dtt:ros>0</dtt:ros>
</dtt:S>
<dtt:S>
<dtt:ico>03657001</dtt:ico>
<dtt:pf>101</dtt:pf>
<dtt:ojm>Charles Edward Stewart III</dtt:ojm>
<dtt:jmn>Praha 7, Holešovice, V zákoutí 1029/4</dtt:jmn>
<dtt:res>0</dtt:res>
<dtt:rzp>0</dtt:rzp>
<dtt:ros>0</dtt:ros>
</dtt:S>
<dtt:S>
<dtt:ico>03930246</dtt:ico>
<dtt:pf>101</dtt:pf>
<dtt:ojm>Veronika Franková</dtt:ojm>
<dtt:jmn>Praha 7, Holešovice, V zákoutí 1029/4</dtt:jmn>
<dtt:res>0</dtt:res>
<dtt:rzp>0</dtt:rzp>
<dtt:dph>0</dtt:dph>
<dtt:p_dph>dic=8961220620</dtt:p_dph>
<dtt:ros>0</dtt:ros>
</dtt:S>
<dtt:S>
<dtt:ico>04686136</dtt:ico>
<dtt:pf>101</dtt:pf>
<dtt:ojm>Miroslav Švehla</dtt:ojm>
<dtt:jmn>Praha 7, Holešovice, V zákoutí 1029/4</dtt:jmn>
<dtt:res>0</dtt:res>
<dtt:rzp>0</dtt:rzp>
<dtt:ros>0</dtt:ros>
</dtt:S>
<dtt:S>
<dtt:ico>06547711</dtt:ico>
<dtt:pf>101</dtt:pf>
<dtt:ojm>Ivan Markovych</dtt:ojm>
<dtt:jmn>Praha 7, Holešovice, V zákoutí 1029/4</dtt:jmn>
<dtt:res>0</dtt:res>
<dtt:rzp>0</dtt:rzp>
<dtt:ros>0</dtt:ros>
</dtt:S>
</dtt:V>
<dtt:Pocet_zaznamu>14</dtt:Pocet_zaznamu>
<dtt:Filtr>1</dtt:Filtr>
</are:Odpoved>
</are:Ares_odpovedi>
