<?xml version="1.0" encoding="UTF-8"?>
<are:Ares_odpovedi vystup_format="XML" odpoved_typ="es" Id="ares" xsi:schemaLocation="http://wwwinfo.mfcr.cz/ares/xml_doc/schemas/ares/ares_answer_es/v_1.0.0 http://wwwinfo.mfcr.cz/ares/xml_doc/schemas/ares/ares_answer_es/v_1.0.0/ares_answer_es.xsd" xmlns:are="http://wwwinfo.mfcr.cz/ares/xml_doc/schemas/ares/ares_answer_es/v_1.0.0" xmlns:dtt="http://wwwinfo.mfcr.cz/ares/xml_doc/schemas/ares/ares_datatypes/v_1.0.4" xmlns:udt="http://wwwinfo.mfcr.cz/ares/xml_doc/schemas/uvis_datatypes/v_1.0.1" xmlns:xsi="http://www.w3.org/2001/XMLSchema-instance">
<are:Odpoved>
<dtt:V>
<dtt:S>
<dtt:ico>24200760</dtt:ico>
<dtt:pf>112</dtt:pf>
<dtt:ojm>TRE-MLI s.r.o.</dtt:ojm>
<dtt:jmn>Praha 7, Holešovice, Jankovcova 1055/13</dtt:jmn>
<dtt:or>0</dtt:or>
<dtt:res>0</dtt:res>
<dtt:rzp>0</dtt:rzp>
<dtt:dph>0</dtt:dph>
<dtt:p_dph>dic=24200760</dtt:p_dph>
<dtt:ros>0</dtt:ros>
</dtt:S>
<dtt:S>
<dtt:ico>24248096</dtt:ico>
<dtt:pf>121</dtt:pf>
<dtt:ojm>SSGD INTERNATIONAL a.s.</dtt:ojm>
<dtt:jmn>Praha 7, Holešovice, Jankovcova 1055/13</dtt:jmn>
<dtt:or>0</dtt:or>
<dtt:res>0</dtt:res>
<dtt:rzp>0</dtt:rzp>
<dtt:dph>0</dtt:dph>
<dtt:p_dph>dic=24248096</dtt:p_dph>
<dtt:cedr>0</dtt:cedr>
<dtt:p_cedr>ico=24248096</dtt:p_cedr>
<dtt:ros>0</dtt:ros>
</dtt:S>
<dtt:S>
<dtt:ico>24266612</dtt:ico>
<dtt:pf>112</dtt:pf>
<dtt:ojm>GASTROCORP s.r.o.</dtt:ojm>
<dtt:jmn>Praha 7, Holešovice, Jankovcova 1055/13</dtt:jmn>
<dtt:or>0</dtt:or>
<dtt:res>0</dtt:res>
<dtt:rzp>0</dtt:rzp>
<dtt:dph>0</dtt:dph>
<dtt:p_dph>dic=24266612</dtt:p_dph>
<dtt:ros>0</dtt:ros>
</dtt:S>
<dtt:S>
<dtt:ico>24854077</dtt:ico>
<dtt:pf>112</dtt:pf>
<dtt:ojm>Moderní stěrky s.r.o.</dtt:ojm>
<dtt:jmn>Praha 7, Holešovice, Jankovcova 1055/13</dtt:jmn>
<dtt:or>0</dtt:or>
<dtt:res>0</dtt:res>
<dtt:rzp>0</dtt:rzp>
<dtt:dph>0</dtt:dph>
<dtt:p_dph>dic=24854077</dtt:p_dph>
<dtt:ros>0</dtt:ros>
</dtt:S>
<dtt:S>
<dtt:ico>25226274</dtt:ico>
<dtt:pf>112</dtt:pf>
<dtt:ojm>NET BAG s.r.o.</dtt:ojm>
<dtt:jmn>Praha 7, Holešovice, Jankovcova 1055/13</dtt:jmn>
<dtt:or>0</dtt:or>
<dtt:res>0</dtt:res>
<dtt:rzp>0</dtt:rzp>
<dtt:dph>0</dtt:dph>
<dtt:p_dph>dic=25226274</dtt:p_dph>
<dtt:ros>0</dtt:ros>
</dtt:S>
<dtt:S>
<dtt:ico>25631551</dtt:ico>
<dtt:pf>112</dtt:pf>
<dtt:ojm>Telecon Group s.r.o.</dtt:ojm>
<dtt:jmn>Praha 7, Holešovice, Jankovcova 1055/13</dtt:jmn>
<dtt:or>0</dtt:or>
<dtt:res>0</dtt:res>
<dtt:rzp>0</dtt:rzp>
<dtt:dph>0</dtt:dph>
<dtt:p_dph>dic=25631551</dtt:p_dph>
<dtt:ros>0</dtt:ros>
</dtt:S>
<dtt:S>
<dtt:ico>26509172</dtt:ico>
<dtt:pf>112</dtt:pf>
<dtt:ojm>PRO-CONSULT s.r.o.</dtt:ojm>
<dtt:jmn>Praha 7, Holešovice, Jankovcova 1055/13</dtt:jmn>
<dtt:or>0</dtt:or>
<dtt:res>0</dtt:res>
<dtt:rzp>0</dtt:rzp>
<dtt:dph>0</dtt:dph>
<dtt:p_dph>dic=26509172</dtt:p_dph>
<dtt:ros>0</dtt:ros>
</dtt:S>
<dtt:S>
<dtt:ico>48588539</dtt:ico>
<dtt:pf>112</dtt:pf>
<dtt:ojm>Berka Bros, s.r.o.</dtt:ojm>
<dtt:jmn>Praha 7, Holešovice, Jankovcova 1055/13</dtt:jmn>
<dtt:or>0</dtt:or>
<dtt:res>0</dtt:res>
<dtt:rzp>0</dtt:rzp>
<dtt:dph>0</dtt:dph>
<dtt:p_dph>dic=48588539</dtt:p_dph>
<dtt:cedr>0</dtt:cedr>
<dtt:p_cedr>ico=48588539</dtt:p_cedr>
<dtt:ros>0</dtt:ros>
</dtt:S>
<dtt:S>
<dtt:ico>62577514</dtt:ico>
<dtt:pf>112</dtt:pf>
<dtt:ojm>ORIENTEX, spol. s r.o.</dtt:ojm>
<dtt:jmn>Praha 7, Holešovice, Jankovcova 1055/13</dtt:jmn>
<dtt:or>0</dtt:or>
<dtt:res>0</dtt:res>
<dtt:rzp>0</dtt:rzp>
<dtt:ros>0</dtt:ros>
</dtt:S>
<dtt:S>
<dtt:ico>63674815</dtt:ico>
<dtt:pf>112</dtt:pf>
<dtt:ojm>ARKOS, s.r.o.</dtt:ojm>
<dtt:jmn>Praha 7, Holešovice, Jankovcova 1055/13</dtt:jmn>
<dtt:or>0</dtt:or>
<dtt:res>0</dtt:res>
<dtt:rzp>0</dtt:rzp>
<dtt:dph>0</dtt:dph>
<dtt:p_dph>dic=63674815</dtt:p_dph>
<dtt:ros>0</dtt:ros>
</dtt:S>
<dtt:S>
<dtt:ico>75051303</dtt:ico>
<dtt:pf>736</dtt:pf>
<dtt:ojm>Klub personalistů České republiky - regionální sekce pro Prahu a Středočeský kraj</dtt:ojm>
<dtt:jmn>Praha 7, Holešovice, Jankovcova 1055/13</dtt:jmn>
<dtt:or>0</dtt:or>
<dtt:res>0</dtt:res>
<dtt:cedr>0</dtt:cedr>
<dtt:p_cedr>ico=75051303</dtt:p_cedr>
<dtt:ros>0</dtt:ros>
</dtt:S>
<dtt:S>
<dtt:ico>01753789</dtt:ico>
<dtt:pf>112</dtt:pf>
<dtt:ojm>Pixie Crew Group s.r.o.</dtt:ojm>
<dtt:jmn>Praha 7, Holešovice, Jankovcova 1055/13</dtt:jmn>
<dtt:or>0</dtt:or>
<dtt:res>0</dtt:res>
<dtt:rzp>0</dtt:rzp>
<dtt:dph>0</dtt:dph>
<dtt:p_dph>dic=01753789</dtt:p_dph>
<dtt:cedr>0</dtt:cedr>
<dtt:p_cedr>ico=1753789</dtt:p_cedr>
<dtt:ros>0</dtt:ros>
</dtt:S>
<dtt:S>
<dtt:ico>03639614</dtt:ico>
<dtt:pf>112</dtt:pf>
<dtt:ojm>Pixie Crew s.r.o.</dtt:ojm>
<dtt:jmn>Praha 7, Holešovice, Jankovcova 1055/13</dtt:jmn>
<dtt:or>0</dtt:or>
<dtt:res>0</dtt:res>
<dtt:rzp>0</dtt:rzp>
<dtt:dph>0</dtt:dph>
<dtt:p_dph>dic=03639614</dtt:p_dph>
<dtt:ros>0</dtt:ros>
</dtt:S>
<dtt:S>
<dtt:ico>06249400</dtt:ico>
<dtt:pf>424</dtt:pf>
<dtt:ojm>Ing. Ján Perlác</dtt:ojm>
<dtt:jmn>Praha 7, Holešovice, Jankovcova 1055/13</dtt:jmn>
<dtt:res>0</dtt:res>
<dtt:rzp>0</dtt:rzp>
<dtt:dph>0</dtt:dph>
<dtt:p_dph>dic=684228528</dtt:p_dph>
<dtt:ros>0</dtt:ros>
</dtt:S>
<dtt:S>
<dtt:ico>06818218</dtt:ico>
<dtt:pf>112</dtt:pf>
<dtt:ojm>Museum of Illusions, s.r.o.</dtt:ojm>
<dtt:jmn>Praha 7, Holešovice, Jankovcova 1055/13</dtt:jmn>
<dtt:or>0</dtt:or>
<dtt:res>0</dtt:res>
<dtt:rzp>0</dtt:rzp>
<dtt:ros>0</dtt:ros>
</dtt:S>
<dtt:S>
<dtt:ico>07873417</dtt:ico>
<dtt:pf>112</dtt:pf>
<dtt:ojm>Honza Food, s.r.o.</dtt:ojm>
<dtt:jmn>Praha 7, Holešovice, Jankovcova 1055/13</dtt:jmn>
<dtt:or>0</dtt:or>
<dtt:res>0</dtt:res>
<dtt:rzp>0</dtt:rzp>
<dtt:dph>0</dtt:dph>
<dtt:p_dph>dic=07873417</dtt:p_dph>
<dtt:ros>0</dtt:ros>
</dtt:S>
</dtt:V>
<dtt:Pocet_zaznamu>16</dtt:Pocet_zaznamu>
<dtt:Filtr>1</dtt:Filtr>
</are:Odpoved>
</are:Ares_odpovedi>
