<?xml version="1.0" encoding="UTF-8"?>
<are:Ares_odpovedi vystup_format="XML" odpoved_typ="es" Id="ares" xsi:schemaLocation="http://wwwinfo.mfcr.cz/ares/xml_doc/schemas/ares/ares_answer_es/v_1.0.0 http://wwwinfo.mfcr.cz/ares/xml_doc/schemas/ares/ares_answer_es/v_1.0.0/ares_answer_es.xsd" xmlns:are="http://wwwinfo.mfcr.cz/ares/xml_doc/schemas/ares/ares_answer_es/v_1.0.0" xmlns:dtt="http://wwwinfo.mfcr.cz/ares/xml_doc/schemas/ares/ares_datatypes/v_1.0.4" xmlns:udt="http://wwwinfo.mfcr.cz/ares/xml_doc/schemas/uvis_datatypes/v_1.0.1" xmlns:xsi="http://www.w3.org/2001/XMLSchema-instance">
<are:Odpoved>
<dtt:V>
<dtt:S>
<dtt:ico>00789356</dtt:ico>
<dtt:pf>101</dtt:pf>
<dtt:ojm>Yelizaveta Khromey</dtt:ojm>
<dtt:jmn>Praha 7, Holešovice, Schnirchova 199/11</dtt:jmn>
<dtt:res>0</dtt:res>
<dtt:rzp>0</dtt:rzp>
<dtt:ros>0</dtt:ros>
</dtt:S>
<dtt:S>
<dtt:ico>01161466</dtt:ico>
<dtt:pf>101</dtt:pf>
<dtt:ojm>Zuzana Savková</dtt:ojm>
<dtt:jmn>Praha 7, Holešovice, Schnirchova 199/11</dtt:jmn>
<dtt:res>0</dtt:res>
<dtt:rzp>0</dtt:rzp>
<dtt:ros>0</dtt:ros>
</dtt:S>
<dtt:S>
<dtt:ico>42518709</dtt:ico>
<dtt:pf>101</dtt:pf>
<dtt:ojm>Helena Ziková</dtt:ojm>
<dtt:jmn>Praha 7, Holešovice, Schnirchova 199/11</dtt:jmn>
<dtt:res>0</dtt:res>
<dtt:rzp>0</dtt:rzp>
<dtt:ros>0</dtt:ros>
</dtt:S>
<dtt:S>
<dtt:ico>43926011</dtt:ico>
<dtt:pf>101</dtt:pf>
<dtt:ojm>Ing. Antonín Jankovský</dtt:ojm>
<dtt:jmn>Praha 7, Holešovice, Schnirchova 199/11</dtt:jmn>
<dtt:res>0</dtt:res>
<dtt:rzp>0</dtt:rzp>
<dtt:ros>0</dtt:ros>
</dtt:S>
<dtt:S>
<dtt:ico>43933505</dtt:ico>
<dtt:pf>101</dtt:pf>
<dtt:ojm>Filip JANEK</dtt:ojm>
<dtt:jmn>Praha 7, Holešovice, Schnirchova 199/11</dtt:jmn>
<dtt:res>0</dtt:res>
<dtt:rzp>0</dtt:rzp>
<dtt:ros>0</dtt:ros>
</dtt:S>
<dtt:S>
<dtt:ico>47092122</dtt:ico>
<dtt:pf>101</dtt:pf>
<dtt:ojm>Klára Basjuk</dtt:ojm>
<dtt:jmn>Praha 7, Holešovice, Schnirchova 199/11</dtt:jmn>
<dtt:res>0</dtt:res>
<dtt:rzp>0</dtt:rzp>
<dtt:ros>0</dtt:ros>
</dtt:S>
<dtt:S>
<dtt:ico>67992692</dtt:ico>
<dtt:pf>105</dtt:pf>
<dtt:ojm>Františka Hamsíková, BcA.</dtt:ojm>
<dtt:jmn>Praha 7, Holešovice, Schnirchova 199/11</dtt:jmn>
<dtt:res>0</dtt:res>
<dtt:rzp>0</dtt:rzp>
<dtt:ros>0</dtt:ros>
</dtt:S>
<dtt:S>
<dtt:ico>69512060</dtt:ico>
<dtt:pf>101</dtt:pf>
<dtt:ojm>Daniela Faustová</dtt:ojm>
<dtt:jmn>Praha 7, Holešovice, Schnirchova 199/11</dtt:jmn>
<dtt:res>0</dtt:res>
<dtt:rzp>0</dtt:rzp>
<dtt:ros>0</dtt:ros>
</dtt:S>
<dtt:S>
<dtt:ico>70348774</dtt:ico>
<dtt:pf>101</dtt:pf>
<dtt:ojm>Kateřina Lančová</dtt:ojm>
<dtt:jmn>Praha 7, Holešovice, Schnirchova 199/11</dtt:jmn>
<dtt:res>0</dtt:res>
<dtt:rzp>0</dtt:rzp>
<dtt:ros>0</dtt:ros>
</dtt:S>
<dtt:S>
<dtt:ico>71318755</dtt:ico>
<dtt:pf>101</dtt:pf>
<dtt:ojm>Michal Dlouhý</dtt:ojm>
<dtt:jmn>Praha 7, Holešovice, Schnirchova 199/11</dtt:jmn>
<dtt:res>0</dtt:res>
<dtt:rzp>0</dtt:rzp>
<dtt:ros>0</dtt:ros>
</dtt:S>
<dtt:S>
<dtt:ico>71573585</dtt:ico>
<dtt:pf>101</dtt:pf>
<dtt:ojm>Vladimir Basjuk</dtt:ojm>
<dtt:jmn>Praha 7, Holešovice, Schnirchova 199/11</dtt:jmn>
<dtt:res>0</dtt:res>
<dtt:rzp>0</dtt:rzp>
<dtt:ros>0</dtt:ros>
</dtt:S>
<dtt:S>
<dtt:ico>71615857</dtt:ico>
<dtt:pf>101</dtt:pf>
<dtt:ojm>Hana Vítková</dtt:ojm>
<dtt:jmn>Praha 7, Holešovice, Schnirchova 199/11</dtt:jmn>
<dtt:res>0</dtt:res>
<dtt:rzp>0</dtt:rzp>
<dtt:ros>0</dtt:ros>
</dtt:S>
<dtt:S>
<dtt:ico>71672630</dtt:ico>
<dtt:pf>101</dtt:pf>
<dtt:ojm>Eva KUPKOVÁ</dtt:ojm>
<dtt:jmn>Praha 7, Holešovice, Schnirchova 199/11</dtt:jmn>
<dtt:res>0</dtt:res>
<dtt:rzp>0</dtt:rzp>
<dtt:ros>0</dtt:ros>
</dtt:S>
<dtt:S>
<dtt:ico>71889817</dtt:ico>
<dtt:pf>101</dtt:pf>
<dtt:ojm>Bc. Věra Witkovská</dtt:ojm>
<dtt:jmn>Praha 7, Holešovice, Schnirchova 199/11</dtt:jmn>
<dtt:res>0</dtt:res>
<dtt:rzp>0</dtt:rzp>
<dtt:ros>0</dtt:ros>
</dtt:S>
<dtt:S>
<dtt:ico>75764024</dtt:ico>
<dtt:pf>101</dtt:pf>
<dtt:ojm>MgA. Lukáš Tůma</dtt:ojm>
<dtt:jmn>Praha 7, Holešovice, Schnirchova 199/11</dtt:jmn>
<dtt:res>0</dtt:res>
<dtt:rzp>0</dtt:rzp>
<dtt:ros>0</dtt:ros>
</dtt:S>
<dtt:S>
<dtt:ico>04964357</dtt:ico>
<dtt:pf>101</dtt:pf>
<dtt:ojm>Johana Janková</dtt:ojm>
<dtt:jmn>Praha 7, Holešovice, Schnirchova 199/11</dtt:jmn>
<dtt:res>0</dtt:res>
<dtt:rzp>0</dtt:rzp>
<dtt:ros>0</dtt:ros>
</dtt:S>
</dtt:V>
<dtt:Pocet_zaznamu>16</dtt:Pocet_zaznamu>
<dtt:Filtr>1</dtt:Filtr>
</are:Odpoved>
</are:Ares_odpovedi>
